FactorioAPI/Utils.py
FactorioAPI/__init__.py
FactorioAPI/API/__init__.py
FactorioAPI/API/Internal/__init__.py
FactorioAPI/API/Internal/download.py
FactorioAPI/API/Internal/matchmaking.py
FactorioAPI/API/Internal/modPortal.py
FactorioAPI/API/Internal/webAuth.py
FactorioAPI/API/Public/__init__.py
FactorioAPI/API/Public/modDetails.py
FactorioAPI/API/Public/modImages.py
FactorioAPI/API/Public/modPublish.py
FactorioAPI/API/Public/modUpload.py
FactorioAPI/Data/Utils.py
FactorioAPI/Data/__init__.py
FactorioAPI/Data/Files/__init__.py
FactorioAPI/Data/Files/achievements.py
FactorioAPI/Data/Files/modSettings.py
FactorioAPI/Data/IO/__init__.py
FactorioAPI/Data/IO/read.py
FactorioAPI/Data/IO/write.py
FactorioAPI/Data/Strings/__init__.py
FactorioAPI/Data/Strings/blueprints.py
FactorioAPI/Data/Strings/mapExchange.py
tests/__init__.py
tests/test-modSettings.py
FactorioAPI-1.1.3.dist-info/LICENSE
FactorioAPI-1.1.3.dist-info/METADATA
FactorioAPI-1.1.3.dist-info/WHEEL
FactorioAPI-1.1.3.dist-info/top_level.txt
FactorioAPI-1.1.3.dist-info/RECORD
