Metadata-Version: 2.1
Name: FactorioAPI
Version: 1.1.3
Summary: A Python library to interact with the Factorio API and related files
Author: Cat Lord
Project-URL: Homepage, https://github.com/catlord-dev/factorioapi
Project-URL: Issues, https://github.com/catlord-dev/factorioapi/issues
Classifier: Programming Language :: Python :: 3.13
Classifier: License :: OSI Approved :: GNU Affero General Public License v3
Classifier: Operating System :: OS Independent
Requires-Python: >=3.13
License-File: LICENSE
